setup.py
mikoto/__init__.py
mikoto.egg-info/PKG-INFO
mikoto.egg-info/SOURCES.txt
mikoto.egg-info/dependency_links.txt
mikoto.egg-info/entry_points.txt
mikoto.egg-info/requires.txt
mikoto.egg-info/top_level.txt
mikoto/libs/__init__.py
mikoto/libs/consts.py
mikoto/libs/emoji.py
mikoto/libs/mock.py
mikoto/libs/text.py
tests/__init__.py
tests/test_markdown.py
tests/test_utils.py