Metadata-Version: 1.0
Name: mikoto
Version: 0.0.4
Summary: better Markdown Render
Home-page: https://github.com/qingfeng/mikoto
Author: qingfeng
Author-email: qingfeng@douban.com
License: New BSD
Keywords: markdown,Douban
Platform: any
